python_solvespace/__init__.pxd
python_solvespace/__init__.py
python_solvespace/py.typed
python_solvespace/slvs.cp36-win_amd64.pyd
python_solvespace/slvs.pxd
python_solvespace/slvs.pyi
python_solvespace/slvs.pyx
python_solvespace-3.0.8.dist-info/METADATA
python_solvespace-3.0.8.dist-info/WHEEL
python_solvespace-3.0.8.dist-info/top_level.txt
python_solvespace-3.0.8.dist-info/RECORD
