Metadata-Version: 2.1
Name: python-solvespace
Version: 3.0.8
Summary: Python library of Solvespace.
Home-page: https://github.com/KmolYuan/solvespace
Author: Yuan Chang
Author-email: pyslvs@gmail.com
License: GPLv3+
Keywords: cad,mechanical-engineering,2d,3d
Platform: UNKNOWN
Classifier: Programming Language :: Python :: 3.6
Classifier: Programming Language :: Python :: 3.7
Classifier: Programming Language :: Python :: 3.8
Classifier: Programming Language :: Python :: 3.9
Classifier: Programming Language :: Python :: 3.10
Classifier: Programming Language :: Python :: 3.11
Classifier: Programming Language :: Cython
Classifier: Topic :: Scientific/Engineering
Classifier: License :: OSI Approved :: GNU General Public License v3 or later (GPLv3+)
Classifier: Operating System :: OS Independent
Classifier: Typing :: Typed
Requires-Python: >=3.6
